CHANGES.rst
LICENSE.txt
MANIFEST.in
README.rst
requirements-testing.txt
setup.py
wsgi_statsd/__init__.py
wsgi_statsd.egg-info/PKG-INFO
wsgi_statsd.egg-info/SOURCES.txt
wsgi_statsd.egg-info/dependency_links.txt
wsgi_statsd.egg-info/requires.txt
wsgi_statsd.egg-info/top_level.txt